Workbook
Name _ftn1: 'Part B SCENARIO'!$A$23
Name _ftnref1: 'Part B SCENARIO'!$C$3

Sheet Part A
A1: ANNEX 6 - MODEL FINANCIAL OFFER
A2: Name of Tenderer:
A4: Part A - PRICE LIST - All (and only) cells in yellow are to be completed by the tenderer!
A5: Item+A5:C25 | B5: Description | C5: Unit | D5: Price per Unit in EURO | E5: Weighting in % | F5: Weighted Price per man/hour
A6: 1 | B6: Senior project manager (min. 10 years relevant exp.) | C6: man/hour | E6: 2 | F6: =D6*(E6/100) -> 0
A7: 2 | B7: Project manager (min. 5 years relevant experience) | C7: man/hour | E7: 4 | F7: =D7*(E7/100) -> 0
A8: 3 | B8: Senior web developer (min.10 years relevant exp.) | C8: man/hour | E8: 2 | F8: =D8*(E8/100) -> 0
A9: 4 | B9: Web developer (min. 5 years relevant experience) | C9: man/hour | E9: 4 | F9: =D9*(E9/100) -> 0
A10: 5 | B10: Junior web developer (min. 2 years relevant experience) | C10: man/hour | E10: 10 | F10: =D10*(E10/100) -> 0
A11: 6 | B11: Senior Drupal developer (min.10 years relevant experience) | C11: man/hour | E11: 2 | F11: =D11*(E11/100) -> 0
A12: 7 | B12: Drupal developer (min. 5 years relevant experience) | C12: man/hour | E12: 6 | F12: =D12*(E12/100) -> 0
A13: 8 | B13: Junior Drupal developer (min. 2 years relevant experience) | C13: man/hour | E13: 10 | F13: =D13*(E13/100) -> 0
A14: 9 | B14: User experiences expert (min. 5 years relevant experience) | C14: man/hour | E14: 2 | F14: =D14*(E14/100) -> 0
A15: 10 | B15: Digital communication campaign expert (min. 5 years relevant experience) | C15: man/hour | E15: 4 | F15: =D15*(E15/100) -> 0
A16: 11 | B16: Web solution architect (min. 5 years relevant exxperience) | C16: man/hour | E16: 2 | F16: =D16*(E16/100) -> 0
A17: 12 | B17: Senior digital content editor (min. 10 years relevant experience) | C17: man/hour | E17: 2 | F17: =D17*(E17/100) -> 0
... A25: 20 | B25: Junior Data/Visualisation/Infographic developer (min. 2 years relevant experience) | C25: man/hour | E25: 10 | F25: =D25*(E25/100) -> 0
A26: Total weighting | E26: =SUM(E6:E25) -> 100
A27: SUM OF WEIGHTED PRICES* *The SUM OF WEIGHTED PRICES is the sum of all the weighted prices of Part A - PRICE LIST | F27: =SUM(F6:F25) -> 0
A28: Note: - The ANNEX 6 - MODEL FINANCIAL OFFER shall be submitted in both pdf and xls format, in case of inconsistencies, the xls format prevails. - While filling in Annex 6 the tenderer shall take into consideration all requirements defined in the Tender Specifications. Failure to comply with these requirements may lead to rejection of the tender. - The financial offer shall not include any notes/additional information/clarifications inserted or attached by the tenderer. Failure to comply with this requirement may lead to rejection of the tender. - Every tenderer is required to verify that the results of all data entered in the model financial offer are correct and ensure that all averages, sub-totals, totals etc. are correct and consistently provided. - A price shall be indicated for each category and must not amount to zero. Failure to comply with this requirement may lead to rejection of the tender. - Please note that the prices indicated in Part A – Price list are maximum prices, and will be binding on the contractor throughout the contract implementation. - Prices must be quoted in EURO and include all expenses necessary to perform the contract, such as equipment required to perform the work. In special cases, where duly justified by the nature of the project and agreed with the Agency a need and/or maximum budget for the following reimbursable costs may be indicated by EASA in the Request for Specific Contract: i. other costs incurred by the contractor linked to the services requested (e.g. hosting services, email deliver services, etc.) -The price quoted is fixed and shall be subject to NO revision. -The financial offer shall be: - expressed in EURO. Tenderers from countries outside the euro zone have to quote their prices in euro. The price quoted may not be revised in line with exchange rate movements. It is for the tenderer to bear the risks or the benefits deriving from any variation. - quoted free of all duties, taxes and other charges, i.e. also free of VAT. - EASA is exempt from such charges in the EU under Articles 3 and 4 of the Protocol on the Privileges and Immunities of the European Union of 8 April 1965 annexed to the Treaty on the Functioning of the European Union. Exemption is granted to EASA by the governments of the Member States, either through refunds upon presentation of documentary evidence or by direct exemption. In case of doubt about the applicable VAT system, it is the tenderer's responsibility to contact his or her national authorities to clarify the way in which the European Union is exempt from VAT. - Costs incurred in preparing and submitting tenders are borne by the tenderer and shall not be reimbursed.

Sheet Part B SCENARIO
A1: Part B – SCENARIO
A3: Description of tasks | B3: Profiles as per Part A | C3: Price per Unit in EURO | D3: Number of Units | E3: Total price in EURO
A4: 1. Dedicated Drupal support for creation of a content type of medium complexity. The content type is for events and has the following fields: Title, body, cover image, location, start/end date, agenda(file), speakers(file), contact, video recording(link); 2. Dedicated Drupal support and front-end development for creation of a calendar view for events. Each event should have a dedicated page, details of the content type ‘events’ are explained in point 1. 3. Data visualisation support to facilitate front end development of a website. Before development starts mockups should be provided to validate the final look and feel. The website should provide the relevant graphical representations(line graphs, bar charts, ...) using existing data visualisation libraries. The data to be used is available via https://www.easa.europa.eu/eco/eaer/topics/overview-of-aviation-sector/figures-and-tables 4. Native app development. Before development starts mockups should be provided to validate the final look and feel. The app should provide the relevant graphical representations(line graphs, bar charts, ...) using existing data visualisation libraries. The data to be used is available via https://www.easa.europa.eu/en/domains/environment/eaer/overview-aviation-sector/figures-and-tables 5. Definition of a digital solution architecture for the website including data management aspects to be used in a scenario where a native app needs to retrieve data and content which is being managed via Drupal. Below is more explanation on the data and content to be managed. - The data to be used is available via https://www.easa.europa.eu/en/domains/environment/eaer/overview-aviation-sector/figures-and-tables - The content should be in the form of news items https://www.easa.europa.eu/en/newsroom-and-events/news and events https://www.easa.europa.eu/en/newsroom-and-events/events 6. Dedicated content editing support for the creation of 2 basic news items and 2 pages including appropriate graphical elements. The news items should introduce the website and the native app mentioned in point 3 and 4 above. The pages should contain content to explain the native app and website. | B4: Project Manager | C4: ='Part A'!D7 -> 0 | D4: 40 | E4: =D4*C4 -> 0
B5: Drupal developer | C5: ='Part A'!D12 -> 0 | D5: 24 | E5: =D5*C5 -> 0
B6: Junior Drupal developer | C6: ='Part A'!D13 -> 0 | D6: 56 | E6: =D6*C6 -> 0
B7: Web developer | C7: ='Part A'!D9 -> 0 | D7: 40 | E7: =D7*C7 -> 0
B8: Junior Web developer | C8: ='Part A'!D10 -> 0 | D8: 80 | E8: =D8*C8 -> 0
B9: Junior digital content editor | C9: ='Part A'!D19 -> 0 | D9: 60 | E9: =D9*C9 -> 0
B10: Data/Visualisation/Infographic developer | C10: ='Part A'!D24 -> 0 | D10: 56 | E10: =D10*C10 -> 0
B11: Web solution architect | C11: ='Part A'!D16 -> 0 | D11: 40 | E11: =D11*C11 -> 0
B12: Native app developer | C12: ='Part A'!D21 -> 0 | D12: 120 | E12: =D12*C12 -> 0
B13: User experience expert | C13: ='Part A'!D14 -> 0 | D13: 56 | E13: =D13*C13 -> 0
A14: TOTAL PRICE* *The TOTAL PRICE is the sum of all the total prices of Part B - SCENARIO | E14: =SUM(E4:E13) -> 0
A16: Note:
A17: ➝ The prices used for the scenario shall be consistent with Part A - PRICE LIST. ➝ Please note that this is only a scenario used for the financial evaluation, it is not binding for the framework contract implementation. However, it shall be used as a benchmark for allocation of resources required during framework contract implementation.
